{"success": true, "results": [{"date": "2021-06-03", "name": "Alabama", "id": "USA_US-AL", "total_count": 3, "lineage_count": 0, "cum_total_count": 214, "cum_lineage_count": 0, "proportion": 0.0, "proportion_ci_lower": 2.2918723990550414e-06, "proportion_ci_upper": 0.011655871632239351}, {"date": "2021-06-04", "name": "Alaska", "id": "USA_US-AK", "total_count": 7, "lineage_count": 0, "cum_total_count": 848, "cum_lineage_count": 7, "proportion": 0.008254716981132075, "proportion_ci_lower": 0.0036996592738825214, "proportion_ci_upper": 0.016138626289589397}, {"date": "2021-06-04", "name": "Arizona", "id": "USA_US-AZ", "total_count": 2, "lineage_count": 0, "cum_total_count": 1678, "cum_lineage_count": 27, "proportion": 0.016090584028605484, "proportion_ci_lower": 0.010872669124748177, "proportion_ci_upper": 0.022973485724950282}, {"date": "2021-06-04", "name": "Arkansas", "id": "USA_US-AR", "total_count": 2, "lineage_count": 0, "cum_total_count": 257, "cum_lineage_count": 0, "proportion": 0.0, "proportion_ci_lower": 1.908780789116022e-06, "proportion_ci_upper": 0.009717067887357975}, {"date": "2021-06-06", "name": "California", "id": "USA_US-CA", "total_count": 10, "lineage_count": 0, "cum_total_count": 6461, "cum_lineage_count": 211, "proportion": 0.03265748336170871, "proportion_ci_lower": 0.028530635515927813, "proportion_ci_upper": 0.03720284899313897}, {"date": "2021-05-17", "name": "California, Los Angeles County", "id": "USA_US-None", "total_count": 1, "lineage_count": 0, "cum_total_count": 3, "cum_lineage_count": 0, "proportion": 0.0, "proportion_ci_lower": 0.00015063602543656854, "proportion_ci_upper": 0.5355832430429506}, {"date": "2021-06-04", "name": "Colorado", "id": "USA_US-CO", "total_count": 6, "lineage_count": 0, "cum_total_count": 5907, "cum_lineage_count": 25, "proportion": 0.004232266802099204, "proportion_ci_lower": 0.002808875082855073, "proportion_ci_upper": 0.0061404596625355135}, {"date": "2021-06-01", "name": "Connecticut", "id": "USA_US-CT", "total_count": 8, "lineage_count": 0, "cum_total_count": 1696, "cum_lineage_count": 1, "proportion": 0.0005896226415094339, "proportion_ci_lower": 6.362624841700895e-05, "proportion_ci_upper": 0.002752626226865673}, {"date": "2021-05-26", "name": "Delaware", "id": "USA_US-DE", "total_count": 1, "lineage_count": 0, "cum_total_count": 511, "cum_lineage_count": 1, "proportion": 0.0019569471624266144, "proportion_ci_lower": 0.00021123106747617792, "proportion_ci_upper": 0.00910989963632669}, {"date": "2021-06-03", "name": "District of Columbia", "id": "USA_US-DC", "total_count": 1, "lineage_count": 0, "cum_total_count": 197, "cum_lineage_count": 0, "proportion": 0.0, "proportion_ci_lower": 2.4893969727681046e-06, "proportion_ci_upper": 0.01265404753124752}, {"date": "2021-06-04", "name": "Florida", "id": "USA_US-FL", "total_count": 14, "lineage_count": 0, "cum_total_count": 7476, "cum_lineage_count": 24, "proportion": 0.0032102728731942215, "proportion_ci_lower": 0.002111505737326066, "proportion_ci_upper": 0.004692875138429309}, {"date": "2021-06-09", "name": "Georgia", "id": "USA_US-GA", "total_count": 8, "lineage_count": 0, "cum_total_count": 1308, "cum_lineage_count": 4, "proportion": 0.0030581039755351682, "proportion_ci_lower": 0.0010331084946223193, "proportion_ci_upper": 0.007255006019465493}, {"date": "2021-05-11", "name": "Guam", "id": "USA_US-None", "total_count": 3, "lineage_count": 0, "cum_total_count": 18, "cum_lineage_count": 0, "proportion": 0.0, "proportion_ci_lower": 2.690311730090928e-05, "proportion_ci_upper": 0.12855821182175955}, {"date": "2021-06-01", "name": "Hawaii", "id": "USA_US-HI", "total_count": 1, "lineage_count": 0, "cum_total_count": 184, "cum_lineage_count": 4, "proportion": 0.021739130434782608, "proportion_ci_lower": 0.0073813220685678554, "proportion_ci_upper": 0.0508534849276453}, {"date": "2021-06-02", "name": "Idaho", "id": "USA_US-ID", "total_count": 1, "lineage_count": 0, "cum_total_count": 181, "cum_lineage_count": 1, "proportion": 0.0055248618784530384, "proportion_ci_lower": 0.0005967669301096304, "proportion_ci_upper": 0.025528645887641588}, {"date": "2021-06-03", "name": "Illinois", "id": "USA_US-IL", "total_count": 7, "lineage_count": 0, "cum_total_count": 5206, "cum_lineage_count": 24, "proportion": 0.004610065309258548, "proportion_ci_lower": 0.003032881385930201, "proportion_ci_upper": 0.006736849603757755}, {"date": "2021-06-06", "name": "Indiana", "id": "USA_US-IN", "total_count": 6, "lineage_count": 0, "cum_total_count": 2424, "cum_lineage_count": 3, "proportion": 0.0012376237623762376, "proportion_ci_lower": 0.0003486894446477477, "proportion_ci_upper": 0.00329921339610717}, {"date": "2021-06-03", "name": "Iowa", "id": "USA_US-IA", "total_count": 1, "lineage_count": 0, "cum_total_count": 171, "cum_lineage_count": 1, "proportion": 0.005847953216374269, "proportion_ci_lower": 0.0006317057624893325, "proportion_ci_upper": 0.02700338433033822}, {"date": "2021-06-11", "name": "Kansas", "id": "USA_US-KS", "total_count": 3, "lineage_count": 0, "cum_total_count": 1227, "cum_lineage_count": 1, "proportion": 0.0008149959250203749, "proportion_ci_lower": 8.795019386866474e-05, "proportion_ci_upper": 0.0038029824069982787}, {"date": "2021-06-04", "name": "Kentucky", "id": "USA_US-KY", "total_count": 2, "lineage_count": 0, "cum_total_count": 554, "cum_lineage_count": 3, "proportion": 0.005415162454873646, "proportion_ci_lower": 0.0015274367659732812, "proportion_ci_upper": 0.014380298460514807}, {"date": "2021-05-27", "name": "Las Vegas", "id": "USA_US-None", "total_count": 2, "lineage_count": 0, "cum_total_count": 42, "cum_lineage_count": 0, "proportion": 0.0, "proportion_ci_lower": 1.162184868730745e-05, "proportion_ci_upper": 0.05771875848759089}, {"date": "2021-06-09", "name": "Louisiana", "id": "USA_US-LA", "total_count": 1, "lineage_count": 0, "cum_total_count": 687, "cum_lineage_count": 0, "proportion": 0.0, "proportion_ci_lower": 7.144915979177377e-07, "proportion_ci_upper": 0.003648392261412009}, {"date": "2021-06-01", "name": "Maine", "id": "USA_US-ME", "total_count": 4, "lineage_count": 0, "cum_total_count": 842, "cum_lineage_count": 0, "proportion": 0.0, "proportion_ci_lower": 5.830031389868047e-07, "proportion_ci_upper": 0.002977976474024921}, {"date": "2021-06-03", "name": "Maryland", "id": "USA_US-MD", "total_count": 4, "lineage_count": 0, "cum_total_count": 2454, "cum_lineage_count": 3, "proportion": 0.0012224938875305623, "proportion_ci_lower": 0.0003444252988456602, "proportion_ci_upper": 0.0032589259677120452}, {"date": "2021-06-04", "name": "Massachusetts", "id": "USA_US-MA", "total_count": 2, "lineage_count": 0, "cum_total_count": 5959, "cum_lineage_count": 20, "proportion": 0.0033562678301728476, "proportion_ci_lower": 0.002116892106208771, "proportion_ci_upper": 0.005076840354245049}, {"date": "2021-06-03", "name": "Michigan", "id": "USA_US-MI", "total_count": 2, "lineage_count": 0, "cum_total_count": 3197, "cum_lineage_count": 7, "proportion": 0.002189552705661558, "proportion_ci_lower": 0.0009798937161604776, "proportion_ci_upper": 0.004294222480561105}, {"date": "2021-06-06", "name": "Minnesota", "id": "USA_US-MN", "total_count": 2, "lineage_count": 0, "cum_total_count": 7284, "cum_lineage_count": 110, "proportion": 0.015101592531576058, "proportion_ci_lower": 0.012489941711518232, "proportion_ci_upper": 0.018098350568811594}, {"date": "2021-06-04", "name": "Mississippi", "id": "USA_US-MS", "total_count": 1, "lineage_count": 0, "cum_total_count": 221, "cum_lineage_count": 0, "proportion": 0.0, "proportion_ci_lower": 2.2193613564976593e-06, "proportion_ci_upper": 0.011289189147385454}, {"date": "2021-06-04", "name": "Missouri", "id": "USA_US-MO", "total_count": 1, "lineage_count": 0, "cum_total_count": 787, "cum_lineage_count": 2, "proportion": 0.0025412960609911056, "proportion_ci_lower": 0.0005284529697829301, "proportion_ci_upper": 0.008127374630254702}, {"date": "2021-06-08", "name": "Montana", "id": "USA_US-MT", "total_count": 8, "lineage_count": 0, "cum_total_count": 368, "cum_lineage_count": 13, "proportion": 0.035326086956521736, "proportion_ci_lower": 0.019943091795353005, "proportion_ci_upper": 0.057963009160615364}, {"date": "2021-06-10", "name": "Nebraska", "id": "USA_US-NE", "total_count": 1, "lineage_count": 0, "cum_total_count": 426, "cum_lineage_count": 2, "proportion": 0.004694835680751174, "proportion_ci_lower": 0.0009768450196554475, "proportion_ci_upper": 0.014974980353609446}, {"date": "2021-06-02", "name": "Nevada", "id": "USA_US-NV", "total_count": 3, "lineage_count": 0, "cum_total_count": 384, "cum_lineage_count": 8, "proportion": 0.020833333333333332, "proportion_ci_lower": 0.009897314798014664, "proportion_ci_upper": 0.038923246461966654}, {"date": "2021-06-01", "name": "New Hampshire", "id": "USA_US-NH", "total_count": 2, "lineage_count": 0, "cum_total_count": 668, "cum_lineage_count": 0, "proportion": 0.0, "proportion_ci_lower": 7.348063506264097e-07, "proportion_ci_upper": 0.0037519301976079024}, {"date": "2021-06-07", "name": "New Jersey", "id": "USA_US-NJ", "total_count": 11, "lineage_count": 0, "cum_total_count": 2302, "cum_lineage_count": 3, "proportion": 0.0013032145960034753, "proportion_ci_lower": 0.0003671757252903742, "proportion_ci_upper": 0.0034738539769874066}, {"date": "2021-06-03", "name": "New Mexico", "id": "USA_US-NM", "total_count": 1, "lineage_count": 0, "cum_total_count": 801, "cum_lineage_count": 7, "proportion": 0.008739076154806492, "proportion_ci_lower": 0.0039172019295992755, "proportion_ci_upper": 0.017081296167563265}, {"date": "2021-06-03", "name": "New York", "id": "USA_US-NY", "total_count": 4, "lineage_count": 0, "cum_total_count": 4899, "cum_lineage_count": 19, "proportion": 0.0038783425188814043, "proportion_ci_lower": 0.002415845908334513, "proportion_ci_upper": 0.0059254346802141145}, {"date": "2021-05-07", "name": "New York, New York County", "id": "USA_US-None", "total_count": 1, "lineage_count": 0, "cum_total_count": 1, "cum_lineage_count": 0, "proportion": 0.0, "proportion_ci_lower": 0.00038558098075590136, "proportion_ci_upper": 0.8532536836904249}, {"date": "2021-06-04", "name": "North Carolina", "id": "USA_US-NC", "total_count": 3, "lineage_count": 0, "cum_total_count": 2552, "cum_lineage_count": 2, "proportion": 0.0007836990595611285, "proportion_ci_lower": 0.0001628895531708558, "proportion_ci_upper": 0.002511784462437383}, {"date": "2021-05-28", "name": "North Dakota", "id": "USA_US-ND", "total_count": 1, "lineage_count": 0, "cum_total_count": 722, "cum_lineage_count": 1, "proportion": 0.0013850415512465374, "proportion_ci_lower": 0.0001494833223618952, "proportion_ci_upper": 0.006455282588491373}, {"date": "2021-04-29", "name": "Northern Mariana Islands", "id": "USA_US-None", "total_count": 1, "lineage_count": 0, "cum_total_count": 1, "cum_lineage_count": 0, "proportion": 0.0, "proportion_ci_lower": 0.00038558098075590136, "proportion_ci_upper": 0.8532536836904249}, {"date": "2021-06-08", "name": "Ohio", "id": "USA_US-OH", "total_count": 1, "lineage_count": 0, "cum_total_count": 2140, "cum_lineage_count": 2, "proportion": 0.0009345794392523365, "proportion_ci_lower": 0.00019425754838228718, "proportion_ci_upper": 0.002994806286080509}, {"date": "2021-06-03", "name": "Oklahoma", "id": "USA_US-OK", "total_count": 1, "lineage_count": 0, "cum_total_count": 129, "cum_lineage_count": 1, "proportion": 0.007751937984496124, "proportion_ci_lower": 0.0008376916195845889, "proportion_ci_upper": 0.035653691167307766}, {"date": "2021-06-04", "name": "Oregon", "id": "USA_US-OR", "total_count": 4, "lineage_count": 0, "cum_total_count": 1706, "cum_lineage_count": 71, "proportion": 0.041617819460726846, "proportion_ci_lower": 0.03290509448835816, "proportion_ci_upper": 0.051883502437900963}, {"date": "2021-06-04", "name": "Pennsylvania", "id": "USA_US-PA", "total_count": 3, "lineage_count": 0, "cum_total_count": 3532, "cum_lineage_count": 3, "proportion": 0.0008493771234428086, "proportion_ci_lower": 0.0002392787754962048, "proportion_ci_upper": 0.002265046274341098}, {"date": "2021-06-02", "name": "Rhode Island", "id": "USA_US-RI", "total_count": 1, "lineage_count": 0, "cum_total_count": 1088, "cum_lineage_count": 0, "proportion": 0.0, "proportion_ci_lower": 4.512147345240007e-07, "proportion_ci_upper": 0.002305578737674519}, {"date": "2021-05-30", "name": "South Carolina", "id": "USA_US-SC", "total_count": 1, "lineage_count": 0, "cum_total_count": 586, "cum_lineage_count": 0, "proportion": 0.0, "proportion_ci_lower": 8.37585174045396e-07, "proportion_ci_upper": 0.004275596795360001}, {"date": "2021-05-23", "name": "South Dakota", "id": "USA_US-SD", "total_count": 1, "lineage_count": 0, "cum_total_count": 97, "cum_lineage_count": 0, "proportion": 0.0, "proportion_ci_lower": 5.049169109898994e-06, "proportion_ci_upper": 0.025498792336140684}, {"date": "2021-06-03", "name": "Tennessee", "id": "USA_US-TN", "total_count": 17, "lineage_count": 0, "cum_total_count": 1110, "cum_lineage_count": 7, "proportion": 0.006306306306306306, "proportion_ci_lower": 0.002825075310861169, "proportion_ci_upper": 0.012341788197855807}, {"date": "2021-06-04", "name": "Texas", "id": "USA_US-TX", "total_count": 8, "lineage_count": 0, "cum_total_count": 5302, "cum_lineage_count": 25, "proportion": 0.004715201810637495, "proportion_ci_lower": 0.0031296298728497834, "proportion_ci_upper": 0.006840352990658438}, {"date": "2021-05-22", "name": "Unknown", "id": "USA_US-None", "total_count": 1, "lineage_count": 0, "cum_total_count": 13, "cum_lineage_count": 0, "proportion": 0.0, "proportion_ci_lower": 3.70519332987658e-05, "proportion_ci_upper": 0.17261944528205697}, {"date": "2021-06-04", "name": "Utah", "id": "USA_US-UT", "total_count": 6, "lineage_count": 0, "cum_total_count": 1117, "cum_lineage_count": 21, "proportion": 0.018800358102059087, "proportion_ci_lower": 0.012028292083335083, "proportion_ci_upper": 0.028057299807265457}, {"date": "2021-05-31", "name": "Vermont", "id": "USA_US-VT", "total_count": 1, "lineage_count": 0, "cum_total_count": 465, "cum_lineage_count": 0, "proportion": 0.0, "proportion_ci_lower": 1.0554201580869415e-06, "proportion_ci_upper": 0.0053845742475646975}, {"date": "2021-05-30", "name": "Virgin Islands", "id": "USA_US-None", "total_count": 1, "lineage_count": 0, "cum_total_count": 1, "cum_lineage_count": 0, "proportion": 0.0, "proportion_ci_lower": 0.00038558098075590136, "proportion_ci_upper": 0.8532536836904249}, {"date": "2021-05-09", "name": "Virgin Islands of the U.S.", "id": "USA_US-None", "total_count": 1, "lineage_count": 0, "cum_total_count": 9, "cum_lineage_count": 0, "proportion": 0.0, "proportion_ci_lower": 5.306405341849297e-05, "proportion_ci_upper": 0.23761009863290297}, {"date": "2021-06-03", "name": "Virginia", "id": "USA_US-VA", "total_count": 1, "lineage_count": 0, "cum_total_count": 1378, "cum_lineage_count": 0, "proportion": 0.0, "proportion_ci_lower": 3.562738712396663e-07, "proportion_ci_upper": 0.0018208999020973957}, {"date": "2021-06-08", "name": "Washington", "id": "USA_US-WA", "total_count": 12, "lineage_count": 0, "cum_total_count": 7574, "cum_lineage_count": 71, "proportion": 0.009374174808555584, "proportion_ci_lower": 0.007386788732454627, "proportion_ci_upper": 0.011736212443876237}, {"date": "2021-06-04", "name": "West Virginia", "id": "USA_US-WV", "total_count": 1, "lineage_count": 0, "cum_total_count": 1374, "cum_lineage_count": 0, "proportion": 0.0, "proportion_ci_lower": 3.573108697361865e-07, "proportion_ci_upper": 0.00182619511350827}, {"date": "2021-06-07", "name": "Wisconsin", "id": "USA_US-WI", "total_count": 1, "lineage_count": 0, "cum_total_count": 2318, "cum_lineage_count": 17, "proportion": 0.007333908541846419, "proportion_ci_lower": 0.004442845669187744, "proportion_ci_upper": 0.011451120746269416}, {"date": "2021-06-04", "name": "Wyoming", "id": "USA_US-WY", "total_count": 1, "lineage_count": 0, "cum_total_count": 519, "cum_lineage_count": 13, "proportion": 0.025048169556840076, "proportion_ci_lower": 0.014111107252660121, "proportion_ci_upper": 0.041248586614993754}]}