{"success": true, "results": [{"date": "2021-05-30", "name": "Alabama", "id": "USA_US-AL", "total_count": 1, "lineage_count": 0, "cum_total_count": 213, "cum_lineage_count": 0, "proportion": 0.0, "proportion_ci_lower": 2.302619721994984e-06, "proportion_ci_upper": 0.011710208398741555}, {"date": "2021-06-04", "name": "Alaska", "id": "USA_US-AK", "total_count": 7, "lineage_count": 0, "cum_total_count": 906, "cum_lineage_count": 7, "proportion": 0.00772626931567329, "proportion_ci_lower": 0.0034623731724404963, "proportion_ci_upper": 0.01510960850041887}, {"date": "2021-06-02", "name": "Arizona", "id": "USA_US-AZ", "total_count": 6, "lineage_count": 0, "cum_total_count": 1776, "cum_lineage_count": 31, "proportion": 0.017454954954954954, "proportion_ci_lower": 0.01212277494002832, "proportion_ci_upper": 0.02435623825714195}, {"date": "2021-05-28", "name": "Arkansas", "id": "USA_US-AR", "total_count": 2, "lineage_count": 0, "cum_total_count": 264, "cum_lineage_count": 0, "proportion": 0.0, "proportion_ci_lower": 1.858217152470096e-06, "proportion_ci_upper": 0.009460884291002968}, {"date": "2021-06-01", "name": "California", "id": "USA_US-CA", "total_count": 40, "lineage_count": 1, "cum_total_count": 6503, "cum_lineage_count": 234, "proportion": 0.03598339228048593, "proportion_ci_lower": 0.031661133507626504, "proportion_ci_upper": 0.04071851625376177}, {"date": "2021-05-17", "name": "California, Los Angeles County", "id": "USA_US-None", "total_count": 1, "lineage_count": 0, "cum_total_count": 3, "cum_lineage_count": 0, "proportion": 0.0, "proportion_ci_lower": 0.00015063602543656854, "proportion_ci_upper": 0.5355832430429506}, {"date": "2021-06-01", "name": "Colorado", "id": "USA_US-CO", "total_count": 8, "lineage_count": 0, "cum_total_count": 5328, "cum_lineage_count": 29, "proportion": 0.005442942942942943, "proportion_ci_lower": 0.003725055364852403, "proportion_ci_upper": 0.00769712642671494}, {"date": "2021-05-29", "name": "Connecticut", "id": "USA_US-CT", "total_count": 3, "lineage_count": 0, "cum_total_count": 1973, "cum_lineage_count": 1, "proportion": 0.0005068423720223011, "proportion_ci_lower": 5.46925318431718e-05, "proportion_ci_upper": 0.002366579071508723}, {"date": "2021-05-26", "name": "Delaware", "id": "USA_US-DE", "total_count": 1, "lineage_count": 0, "cum_total_count": 547, "cum_lineage_count": 1, "proportion": 0.0018281535648994515, "proportion_ci_lower": 0.00019732421611592778, "proportion_ci_upper": 0.00851263082769993}, {"date": "2021-06-03", "name": "District of Columbia", "id": "USA_US-DC", "total_count": 1, "lineage_count": 0, "cum_total_count": 204, "cum_lineage_count": 0, "proportion": 0.0, "proportion_ci_lower": 2.4040812749237848e-06, "proportion_ci_upper": 0.012223034718046824}, {"date": "2021-05-31", "name": "Florida", "id": "USA_US-FL", "total_count": 9, "lineage_count": 0, "cum_total_count": 7948, "cum_lineage_count": 25, "proportion": 0.0031454453950679417, "proportion_ci_lower": 0.0020872122740548155, "proportion_ci_upper": 0.004564798598671427}, {"date": "2021-06-09", "name": "Georgia", "id": "USA_US-GA", "total_count": 8, "lineage_count": 0, "cum_total_count": 1325, "cum_lineage_count": 4, "proportion": 0.0030188679245283017, "proportion_ci_lower": 0.0010198427430005875, "proportion_ci_upper": 0.00716213416967848}, {"date": "2021-05-11", "name": "Guam", "id": "USA_US-None", "total_count": 3, "lineage_count": 0, "cum_total_count": 18, "cum_lineage_count": 0, "proportion": 0.0, "proportion_ci_lower": 2.690311730090928e-05, "proportion_ci_upper": 0.12855821182175955}, {"date": "2021-05-28", "name": "Hawaii", "id": "USA_US-HI", "total_count": 1, "lineage_count": 0, "cum_total_count": 214, "cum_lineage_count": 4, "proportion": 0.018691588785046728, "proportion_ci_lower": 0.006341291255078788, "proportion_ci_upper": 0.04382502228971685}, {"date": "2021-05-30", "name": "Idaho", "id": "USA_US-ID", "total_count": 1, "lineage_count": 0, "cum_total_count": 194, "cum_lineage_count": 2, "proportion": 0.010309278350515464, "proportion_ci_lower": 0.002148315348662414, "proportion_ci_upper": 0.032657218759647555}, {"date": "2021-06-01", "name": "Illinois", "id": "USA_US-IL", "total_count": 1, "lineage_count": 0, "cum_total_count": 5525, "cum_lineage_count": 29, "proportion": 0.005248868778280543, "proportion_ci_lower": 0.003592129861709418, "proportion_ci_upper": 0.007422989437072092}, {"date": "2021-06-04", "name": "Indiana", "id": "USA_US-IN", "total_count": 23, "lineage_count": 1, "cum_total_count": 2184, "cum_lineage_count": 3, "proportion": 0.0013736263736263737, "proportion_ci_lower": 0.0003870214979196709, "proportion_ci_upper": 0.003661307272764147}, {"date": "2021-06-03", "name": "Iowa", "id": "USA_US-IA", "total_count": 1, "lineage_count": 0, "cum_total_count": 178, "cum_lineage_count": 1, "proportion": 0.0056179775280898875, "proportion_ci_lower": 0.000606835923505925, "proportion_ci_upper": 0.025953873211542855}, {"date": "2021-06-07", "name": "Kansas", "id": "USA_US-KS", "total_count": 20, "lineage_count": 0, "cum_total_count": 1227, "cum_lineage_count": 1, "proportion": 0.0008149959250203749, "proportion_ci_lower": 8.795019386866474e-05, "proportion_ci_upper": 0.0038029824069982787}, {"date": "2021-05-29", "name": "Kentucky", "id": "USA_US-KY", "total_count": 1, "lineage_count": 0, "cum_total_count": 445, "cum_lineage_count": 4, "proportion": 0.008988764044943821, "proportion_ci_lower": 0.0030415053585319996, "proportion_ci_upper": 0.021229925957564344}, {"date": "2021-05-27", "name": "Las Vegas", "id": "USA_US-None", "total_count": 2, "lineage_count": 0, "cum_total_count": 42, "cum_lineage_count": 0, "proportion": 0.0, "proportion_ci_lower": 1.162184868730745e-05, "proportion_ci_upper": 0.05771875848759089}, {"date": "2021-05-28", "name": "Louisiana", "id": "USA_US-LA", "total_count": 20, "lineage_count": 0, "cum_total_count": 611, "cum_lineage_count": 0, "proportion": 0.0, "proportion_ci_lower": 8.033281313260081e-07, "proportion_ci_upper": 0.004101084922680784}, {"date": "2021-06-01", "name": "Maine", "id": "USA_US-ME", "total_count": 1, "lineage_count": 0, "cum_total_count": 873, "cum_lineage_count": 0, "proportion": 0.0, "proportion_ci_lower": 5.623067854597702e-07, "proportion_ci_upper": 0.00287241159106308}, {"date": "2021-06-03", "name": "Maryland", "id": "USA_US-MD", "total_count": 1, "lineage_count": 0, "cum_total_count": 2556, "cum_lineage_count": 3, "proportion": 0.0011737089201877935, "proportion_ci_lower": 0.00033067617372910984, "proportion_ci_upper": 0.003129015028976667}, {"date": "2021-05-30", "name": "Massachusetts", "id": "USA_US-MA", "total_count": 8, "lineage_count": 0, "cum_total_count": 6531, "cum_lineage_count": 22, "proportion": 0.0033685499923442044, "proportion_ci_lower": 0.002172872635297462, "proportion_ci_upper": 0.005003371330021489}, {"date": "2021-05-29", "name": "Michigan", "id": "USA_US-MI", "total_count": 5, "lineage_count": 0, "cum_total_count": 3479, "cum_lineage_count": 9, "proportion": 0.0025869502730669733, "proportion_ci_lower": 0.0012807850207045095, "proportion_ci_upper": 0.004716141248387373}, {"date": "2021-06-06", "name": "Minnesota", "id": "USA_US-MN", "total_count": 1, "lineage_count": 0, "cum_total_count": 7319, "cum_lineage_count": 113, "proportion": 0.015439267659516327, "proportion_ci_lower": 0.012802767028740464, "proportion_ci_upper": 0.018458771707790644}, {"date": "2021-06-01", "name": "Mississippi", "id": "USA_US-MS", "total_count": 2, "lineage_count": 0, "cum_total_count": 223, "cum_lineage_count": 0, "proportion": 0.0, "proportion_ci_lower": 2.199479106829827e-06, "proportion_ci_upper": 0.011188622445017147}, {"date": "2021-05-30", "name": "Missouri", "id": "USA_US-MO", "total_count": 2, "lineage_count": 0, "cum_total_count": 782, "cum_lineage_count": 2, "proportion": 0.0025575447570332483, "proportion_ci_lower": 0.0005318341719756811, "proportion_ci_upper": 0.008179176631517904}, {"date": "2021-06-02", "name": "Montana", "id": "USA_US-MT", "total_count": 3, "lineage_count": 0, "cum_total_count": 327, "cum_lineage_count": 15, "proportion": 0.045871559633027525, "proportion_ci_lower": 0.027057021055340802, "proportion_ci_upper": 0.07266403712274583}, {"date": "2021-06-07", "name": "Nebraska", "id": "USA_US-NE", "total_count": 1, "lineage_count": 0, "cum_total_count": 437, "cum_lineage_count": 2, "proportion": 0.004576659038901602, "proportion_ci_lower": 0.0009522256372445025, "proportion_ci_upper": 0.014600155396938486}, {"date": "2021-05-30", "name": "Nevada", "id": "USA_US-NV", "total_count": 4, "lineage_count": 0, "cum_total_count": 406, "cum_lineage_count": 11, "proportion": 0.027093596059113302, "proportion_ci_lower": 0.014478242459756988, "proportion_ci_upper": 0.04639862738558509}, {"date": "2021-05-30", "name": "New Hampshire", "id": "USA_US-NH", "total_count": 2, "lineage_count": 0, "cum_total_count": 719, "cum_lineage_count": 0, "proportion": 0.0, "proportion_ci_lower": 6.827033177619509e-07, "proportion_ci_upper": 0.0034863557540797847}, {"date": "2021-05-30", "name": "New Jersey", "id": "USA_US-NJ", "total_count": 5, "lineage_count": 0, "cum_total_count": 2414, "cum_lineage_count": 6, "proportion": 0.0024855012427506215, "proportion_ci_lower": 0.0010380823821703044, "proportion_ci_upper": 0.005116079927107164}, {"date": "2021-05-30", "name": "New Mexico", "id": "USA_US-NM", "total_count": 1, "lineage_count": 0, "cum_total_count": 848, "cum_lineage_count": 7, "proportion": 0.008254716981132075, "proportion_ci_lower": 0.0036996592738825214, "proportion_ci_upper": 0.016138626289589397}, {"date": "2021-06-02", "name": "New York", "id": "USA_US-NY", "total_count": 6, "lineage_count": 0, "cum_total_count": 5352, "cum_lineage_count": 30, "proportion": 0.005605381165919282, "proportion_ci_lower": 0.0038618601096732544, "proportion_ci_upper": 0.007882647153558686}, {"date": "2021-05-07", "name": "New York, New York County", "id": "USA_US-None", "total_count": 1, "lineage_count": 0, "cum_total_count": 1, "cum_lineage_count": 0, "proportion": 0.0, "proportion_ci_lower": 0.00038558098075590136, "proportion_ci_upper": 0.8532536836904249}, {"date": "2021-06-01", "name": "North Carolina", "id": "USA_US-NC", "total_count": 3, "lineage_count": 0, "cum_total_count": 2691, "cum_lineage_count": 2, "proportion": 0.0007432181345224824, "proportion_ci_lower": 0.000154474015359424, "proportion_ci_upper": 0.0023821601112914426}, {"date": "2021-05-24", "name": "North Dakota", "id": "USA_US-ND", "total_count": 8, "lineage_count": 0, "cum_total_count": 785, "cum_lineage_count": 1, "proportion": 0.0012738853503184713, "proportion_ci_lower": 0.00013748357258217778, "proportion_ci_upper": 0.00593859199314728}, {"date": "2021-04-29", "name": "Northern Mariana Islands", "id": "USA_US-None", "total_count": 1, "lineage_count": 0, "cum_total_count": 1, "cum_lineage_count": 0, "proportion": 0.0, "proportion_ci_lower": 0.00038558098075590136, "proportion_ci_upper": 0.8532536836904249}, {"date": "2021-06-01", "name": "Ohio", "id": "USA_US-OH", "total_count": 4, "lineage_count": 0, "cum_total_count": 2081, "cum_lineage_count": 2, "proportion": 0.0009610764055742432, "proportion_ci_lower": 0.00019976652652222825, "proportion_ci_upper": 0.003079614011523124}, {"date": "2021-05-29", "name": "Oklahoma", "id": "USA_US-OK", "total_count": 1, "lineage_count": 0, "cum_total_count": 131, "cum_lineage_count": 1, "proportion": 0.007633587786259542, "proportion_ci_lower": 0.0008248831853422004, "proportion_ci_upper": 0.035118000961210316}, {"date": "2021-06-03", "name": "Oregon", "id": "USA_US-OR", "total_count": 1, "lineage_count": 0, "cum_total_count": 1728, "cum_lineage_count": 72, "proportion": 0.041666666666666664, "proportion_ci_lower": 0.0329994782298048, "proportion_ci_upper": 0.05186690923573711}, {"date": "2021-05-28", "name": "Pennsylvania", "id": "USA_US-PA", "total_count": 12, "lineage_count": 0, "cum_total_count": 3710, "cum_lineage_count": 3, "proportion": 0.0008086253369272237, "proportion_ci_lower": 0.00022779599178260177, "proportion_ci_upper": 0.002156453547207726}, {"date": "2021-05-28", "name": "Rhode Island", "id": "USA_US-RI", "total_count": 1, "lineage_count": 0, "cum_total_count": 1169, "cum_lineage_count": 0, "proportion": 0.0, "proportion_ci_lower": 4.1995676224283483e-07, "proportion_ci_upper": 0.002146030892815493}, {"date": "2021-05-30", "name": "South Carolina", "id": "USA_US-SC", "total_count": 1, "lineage_count": 0, "cum_total_count": 490, "cum_lineage_count": 0, "proportion": 0.0, "proportion_ci_lower": 1.0015996916105597e-06, "proportion_ci_upper": 0.005110694246349163}, {"date": "2021-05-23", "name": "South Dakota", "id": "USA_US-SD", "total_count": 1, "lineage_count": 0, "cum_total_count": 111, "cum_lineage_count": 0, "proportion": 0.0, "proportion_ci_lower": 4.4137728963029014e-06, "proportion_ci_upper": 0.02232611090258803}, {"date": "2021-06-01", "name": "Tennessee", "id": "USA_US-TN", "total_count": 6, "lineage_count": 0, "cum_total_count": 1101, "cum_lineage_count": 7, "proportion": 0.006357856494096276, "proportion_ci_lower": 0.0028482040441369697, "proportion_ci_upper": 0.012442342328910283}, {"date": "2021-06-01", "name": "Texas", "id": "USA_US-TX", "total_count": 3, "lineage_count": 0, "cum_total_count": 5582, "cum_lineage_count": 26, "proportion": 0.004657828735220351, "proportion_ci_lower": 0.0031173092890864115, "proportion_ci_upper": 0.0067109647523996285}, {"date": "2021-05-20", "name": "Unknown", "id": "USA_US-None", "total_count": 2, "lineage_count": 0, "cum_total_count": 15, "cum_lineage_count": 0, "proportion": 0.0, "proportion_ci_lower": 3.2194144323726923e-05, "proportion_ci_upper": 0.15181666211439768}, {"date": "2021-05-31", "name": "Utah", "id": "USA_US-UT", "total_count": 1, "lineage_count": 0, "cum_total_count": 1208, "cum_lineage_count": 25, "proportion": 0.020695364238410598, "proportion_ci_lower": 0.013771244872680543, "proportion_ci_upper": 0.029909162576118975}, {"date": "2021-05-28", "name": "Vermont", "id": "USA_US-VT", "total_count": 1, "lineage_count": 0, "cum_total_count": 479, "cum_lineage_count": 0, "proportion": 0.0, "proportion_ci_lower": 1.0245889206088555e-06, "proportion_ci_upper": 0.005227690382623305}, {"date": "2021-05-30", "name": "Virgin Islands", "id": "USA_US-None", "total_count": 1, "lineage_count": 0, "cum_total_count": 1, "cum_lineage_count": 0, "proportion": 0.0, "proportion_ci_lower": 0.00038558098075590136, "proportion_ci_upper": 0.8532536836904249}, {"date": "2021-05-09", "name": "Virgin Islands of the U.S.", "id": "USA_US-None", "total_count": 1, "lineage_count": 0, "cum_total_count": 10, "cum_lineage_count": 0, "proportion": 0.0, "proportion_ci_lower": 4.789043315758197e-05, "proportion_ci_upper": 0.21719626750921056}, {"date": "2021-06-01", "name": "Virginia", "id": "USA_US-VA", "total_count": 5, "lineage_count": 0, "cum_total_count": 1430, "cum_lineage_count": 0, "proportion": 0.0, "proportion_ci_lower": 3.4332072490361206e-07, "proportion_ci_upper": 0.0017547550592983032}, {"date": "2021-06-03", "name": "Washington", "id": "USA_US-WA", "total_count": 5, "lineage_count": 0, "cum_total_count": 7206, "cum_lineage_count": 65, "proportion": 0.009020260893699695, "proportion_ci_lower": 0.007029396601711795, "proportion_ci_upper": 0.011405165769671877}, {"date": "2021-05-29", "name": "West Virginia", "id": "USA_US-WV", "total_count": 1, "lineage_count": 0, "cum_total_count": 1455, "cum_lineage_count": 0, "proportion": 0.0, "proportion_ci_lower": 3.3742275794341583e-07, "proportion_ci_upper": 0.001724635820597991}, {"date": "2021-06-07", "name": "Wisconsin", "id": "USA_US-WI", "total_count": 1, "lineage_count": 0, "cum_total_count": 1900, "cum_lineage_count": 19, "proportion": 0.01, "proportion_ci_lower": 0.006235795391235884, "proportion_ci_upper": 0.015252230706321757}, {"date": "2021-06-01", "name": "Wyoming", "id": "USA_US-WY", "total_count": 7, "lineage_count": 0, "cum_total_count": 513, "cum_lineage_count": 12, "proportion": 0.023391812865497075, "proportion_ci_lower": 0.012849418380662902, "proportion_ci_upper": 0.039275933620660064}]}